pysync/__init__.py
pysync/__main__.py
pysync/cli.py
pysync/core.py
itm.pysync-1.0.1.dist-info/LICENSE
itm.pysync-1.0.1.dist-info/METADATA
itm.pysync-1.0.1.dist-info/WHEEL
itm.pysync-1.0.1.dist-info/entry_points.txt
itm.pysync-1.0.1.dist-info/top_level.txt
itm.pysync-1.0.1.dist-info/RECORD
