Metadata-Version: 2.1
Name: itm.pysync
Version: 1.0.1
Summary: A simple backup/sync tool with rsync
Home-page: https://github.com/itmammoth/pysync
Author: itmammoth
Author-email: itmammoth@gmail.com
Maintainer: itmammoth
Maintainer-email: itmammoth@gmail.com
License: UNKNOWN
Platform: UNKNOWN
Requires-Python: >=3.5
Requires-Dist: hjson (==3.0.1)
Provides-Extra: dev
Requires-Dist: pytest (>=5) ; extra == 'dev'
